README.txt
setup.cfg
setup.py
unimr.memcachedlock-configure.zcml
docs/HISTORY.txt
unimr/__init__.py
unimr.memcachedlock.egg-info/PKG-INFO
unimr.memcachedlock.egg-info/SOURCES.txt
unimr.memcachedlock.egg-info/dependency_links.txt
unimr.memcachedlock.egg-info/entry_points.txt
unimr.memcachedlock.egg-info/namespace_packages.txt
unimr.memcachedlock.egg-info/not-zip-safe
unimr.memcachedlock.egg-info/requires.txt
unimr.memcachedlock.egg-info/top_level.txt
unimr/memcachedlock/README.txt
unimr/memcachedlock/__init__.py
unimr/memcachedlock/catalog.py
unimr/memcachedlock/config.py
unimr/memcachedlock/configure.zcml
unimr/memcachedlock/memcachedlock.py
unimr/memcachedlock/tests.py
unimr/memcachedlock/wrapper.py
unimr/memcachedlock/zope2.py