Metadata-Version: 1.0
Name: unimr.memcachedlock
Version: 0.1rc2-r144828
Summary: Memcached based locking factory functions to provide shared locking (e.g. bet. zeo-clients)
Home-page: https://svn.plone.org/svn/collective/unimr.memcachedlock
Author: Andreas Gabriel
Author-email: gabriel@hrz.uni-marburg.de
License: GPL
Keywords: ZEO Zope Memcached Lock
Platform: UNKNOWN
Classifier: Framework :: Zope2
Classifier: Programming Language :: Python
Classifier: Topic :: Software Development :: Libraries :: Python Modules
